Metadata-Version: 2.1
Name: FastMSA
Version: 0.3.1
Summary: FastMSA - full-stack framework for microservice architecture applications
Home-page: https://github.com/2021-msa-study/fastmsa
Author: Joseph Kim, Benzamin Yoon
Author-email: cloudeyes@gmail.com
License: MIT
Download-URL: https://github.com/2021-msa-study/fastmsa/archive/v0.3.1.tar.gz
Keywords: fastmsa,microserviceframework,sqlalchemy,fastapi
Platform: UNKNOWN
Classifier: Development Status :: 3 - Alpha
Classifier: Intended Audience :: Developers
Classifier: Topic :: Software Development :: Build Tools
Classifier: License :: OSI Approved :: MIT License
Classifier: Programming Language :: Python :: 3.9
